opencvplus/__init__.py
opencvplus/Images/ColorChannels.py
opencvplus/Images/ColorSpaces.py
opencvplus/Images/__init__.py
open_cv_plus-1.5.dist-info/METADATA
open_cv_plus-1.5.dist-info/WHEEL
open_cv_plus-1.5.dist-info/top_level.txt
open_cv_plus-1.5.dist-info/RECORD
