Metadata-Version: 2.1
Name: open-cv-plus
Version: 1.5
Summary: OpenCV Plus
Home-page: UNKNOWN
Author: TheCoder1001 (Atharv Baluja)
License: UNKNOWN
Keywords: python,opencv
Platform: UNKNOWN
Classifier: Intended Audience :: Developers
Classifier: Programming Language :: Python :: 3
Classifier: Operating System :: Unix
Classifier: Operating System :: MacOS
Classifier: Operating System :: Microsoft :: Windows
